condense_json/__init__.py
condense_json-0.1.1.dist-info/LICENSE
condense_json-0.1.1.dist-info/METADATA
condense_json-0.1.1.dist-info/WHEEL
condense_json-0.1.1.dist-info/top_level.txt
condense_json-0.1.1.dist-info/RECORD
