Metadata-Version: 2.2
Name: condense-json
Version: 0.1.1
Summary: Python function for condensing JSON using replacement strings
Author: Simon Willison
License: Apache-2.0
Project-URL: Homepage, https://github.com/simonw/condense-json
Project-URL: Changelog, https://github.com/simonw/condense-json/releases
Project-URL: Issues, https://github.com/simonw/condense-json/issues
Project-URL: CI, https://github.com/simonw/condense-json/actions
Classifier: License :: OSI Approved :: Apache Software License
Requires-Python: >=3.8
License-File: LICENSE
Provides-Extra: test
Requires-Dist: pytest; extra == "test"
